earthdata/__init__.py
earthdata/auth.py
earthdata/css/iso_bootstrap4.0.0min.css
earthdata/css/styles.css
earthdata/daac.py
earthdata/formatters.py
earthdata/results.py
earthdata/search.py
earthdata/store.py
earthdata/widgets.py
earthdata-0.4.1.dist-info/LICENSE
earthdata-0.4.1.dist-info/WHEEL
earthdata-0.4.1.dist-info/METADATA
earthdata-0.4.1.dist-info/RECORD
