Metadata-Version: 2.1
Name: earthdata
Version: 0.4.1
Summary: Client library for NASA Earthdata APIs
License: MIT
Author: Luis Lopez
Author-email: betolin@gmail.com
Requires-Python: >=3.8,<4.0
Classifier: License :: OSI Approved :: MIT License
Classifier: Programming Language :: Python :: 3
Classifier: Programming Language :: Python :: 3.8
Classifier: Programming Language :: Python :: 3.9
Classifier: Programming Language :: Python :: 3.10
Classifier: Programming Language :: Python :: 3.11
Requires-Dist: aiofiles (>=0.8.0)
Requires-Dist: aiohttp (>=3.8.0)
Requires-Dist: fsspec (>=2022.1)
Requires-Dist: multimethod (>=1.8)
Requires-Dist: pqdm (>=0.1)
Requires-Dist: python-benedict (>=0.25)
Requires-Dist: python-cmr (>=0.7)
Requires-Dist: requests (>=2.26)
Requires-Dist: s3fs (>=2021.11,<2024)
Requires-Dist: tinynetrc (>=1.3.1,<2.0.0)
